melting_schemas/__init__.py
melting_schemas/errors.py
melting_schemas/json_schema.py
melting_schemas/pyobjectid.py
melting_schemas/usage.py
melting_schemas/utils.py
melting_schemas/completion/__init__.py
melting_schemas/completion/base_settings.py
melting_schemas/completion/buffered_ml_messages.py
melting_schemas/completion/completion_response.py
melting_schemas/completion/finish_reason.py
melting_schemas/completion/streamed_ml_messages.py
melting_schemas/completion/templating.py
melting_schemas/completion/chat/__init__.py
melting_schemas/completion/chat/examples.py
melting_schemas/completion/chat/requests.py
melting_schemas/completion/chat/settings.py
melting_schemas/completion/tcall/__init__.py
melting_schemas/completion/tcall/examples.py
melting_schemas/completion/tcall/params.py
melting_schemas/completion/tcall/requests.py
melting_schemas/completion/tcall/settings.py
melting_schemas/completion/tcall/specs.py
melting_schemas/completion/text/__init__.py
melting_schemas/completion/text/examples.py
melting_schemas/completion/text/requests.py
melting_schemas/completion/text/settings.py
melting_schemas/encoding/__init__.py
melting_schemas/encoding/embedding.py
melting_schemas/encoding/examples.py
melting_schemas/encoding/text_encoding.py
melting_schemas/templating/__init__.py
melting_schemas/templating/examples.py
melting_schemas/templating/prompt.py
melting_schemas/tools/__init__.py
melting_schemas/tools/examples.py
melting_schemas-3.8.0.dist-info/METADATA
melting_schemas-3.8.0.dist-info/WHEEL
melting_schemas-3.8.0.dist-info/top_level.txt
melting_schemas-3.8.0.dist-info/RECORD
