Metadata-Version: 2.4
Name: melting_schemas
Version: 3.8.0
Summary: Teia MeltingFace API
Author-email: TeiaLabs <contato@teialabs.com>
Requires-Python: >=3.12
Requires-Dist: pydantic[email]>=2.7.0
Provides-Extra: first-party
Requires-Dist: AIPrompts==0.5.6; extra == "first-party"
Provides-Extra: dev
Requires-Dist: black==24.4.*; extra == "dev"
Requires-Dist: isort==5.13.*; extra == "dev"
